README.md
setup.py
mara_google_sheet_downloader/__init__.py
mara_google_sheet_downloader/__main__.py
mara_google_sheet_downloader/columns_definition.py
mara_google_sheet_downloader/config.py
mara_google_sheet_downloader/mara_integration.py
mara_google_sheet_downloader/user_credential_helper.py
mara_google_sheet_downloader.egg-info/PKG-INFO
mara_google_sheet_downloader.egg-info/SOURCES.txt
mara_google_sheet_downloader.egg-info/dependency_links.txt
mara_google_sheet_downloader.egg-info/requires.txt
mara_google_sheet_downloader.egg-info/top_level.txt
tests/__init__.py
tests/test_column_definitions.py
tests/test_mara_integration.py
tests/test_write_rows_as_csv_to_stream.py