Metadata-Version: 2.1
Name: mara-google-sheet-downloader
Version: 1.0.0
Summary: Opinionated lightweight ETL pipeline framework
Home-page: https://github.com/mara/mara-google-sheet-downloader
Author: Mara contributors
License: MIT
Platform: UNKNOWN
Requires-Python: >=3.6
